tsql/__init__.py
tsql/query_builder.py
tsql/row.py
tsql/styles.py
tsql/type_processor.py
t_sql-4.9.3.dist-info/METADATA
t_sql-4.9.3.dist-info/WHEEL
t_sql-4.9.3.dist-info/licenses/LICENSE
t_sql-4.9.3.dist-info/RECORD
