Metadata-Version: 2.4
Name: t-sql
Version: 4.9.3
Summary: Safe SQL. SQL queries for python t-strings (PEP 750)
Project-URL: Homepage, https://github.com/nhumrich/t-sql
License-File: LICENSE
Requires-Python: >=3.14
Requires-Dist: alembic>=1.17.0
